dataprof/__init__.py
dataprof/__init__.pyi
dataprof/_dataprof.cpython-313-x86_64-linux-gnu.so
dataprof/py.typed
dataprof-0.5.10.dist-info/METADATA
dataprof-0.5.10.dist-info/WHEEL
dataprof-0.5.10.dist-info/licenses/LICENSE
dataprof-0.5.10.dist-info/licenses/LICENSE-APACHE
dataprof-0.5.10.dist-info/RECORD
