Metadata-Version: 2.4
Name: dataprof
Version: 0.5.10
Classifier: Development Status :: 4 - Beta
Classifier: Intended Audience :: Developers
Classifier: Intended Audience :: Science/Research
Classifier: License :: OSI Approved :: MIT License
Classifier: Operating System :: POSIX
Classifier: Operating System :: Microsoft :: Windows
Classifier: Operating System :: MacOS :: MacOS X
Classifier: Programming Language :: Rust
Classifier: Programming Language :: Python :: Implementation :: CPython
Classifier: Programming Language :: Python :: Implementation :: PyPy
Classifier: Programming Language :: Python :: 3
Classifier: Programming Language :: Python :: 3.8
Classifier: Programming Language :: Python :: 3.9
Classifier: Programming Language :: Python :: 3.10
Classifier: Programming Language :: Python :: 3.11
Classifier: Programming Language :: Python :: 3.12
Classifier: Topic :: Scientific/Engineering
Classifier: Topic :: Software Development :: Libraries :: Python Modules
Requires-Dist: pandas>=1.3.0 ; extra == 'all'
Requires-Dist: ipython>=7.0.0 ; extra == 'all'
Requires-Dist: numpy>=1.20.0 ; extra == 'all'
Requires-Dist: pandas>=1.3.0 ; extra == 'jupyter'
Requires-Dist: ipython>=7.0.0 ; extra == 'jupyter'
Requires-Dist: pandas>=1.3.0 ; extra == 'pandas'
Provides-Extra: all
Provides-Extra: jupyter
Provides-Extra: pandas
License-File: LICENSE
License-File: LICENSE-APACHE
Summary: Fast, lightweight data profiling and quality assessment library
Keywords: data,profiling,quality,csv,json,analysis,performance
Home-Page: https://github.com/AndreaBozzo/dataprof
Author-email: Andrea Bozzo <andreabozzo92@gmail.com>
Requires-Python: >=3.8
Project-URL: Homepage, https://github.com/AndreaBozzo/dataprof
Project-URL: Issues, https://github.com/AndreaBozzo/dataprof/issues
Project-URL: Repository, https://github.com/AndreaBozzo/dataprof
